[
  {
    "houseId": 1,
    "name": "Et qui velit commodo labore fugiat enim et Lorem laborum ut.",
    "price": 204158,
    "description": "Laboris ut excepteur anim consectetur elit elit sint.",
    "address": "Id eiusmod fugiat eiusmod anim.",
    "longitude": -142.232042,
    "latitude": 68.92302,
    "image": [
      "https://realestatemgt.s3.ap-southeast-1.amazonaws.com/dataset/487/487_bathroom.jpg",
      "https://realestatemgt.s3.ap-southeast-1.amazonaws.com/dataset/487/487_kitchen.jpg",
      "https://realestatemgt.s3.ap-southeast-1.amazonaws.com/dataset/487/487_bedroom.jpg",
      "https://realestatemgt.s3.ap-southeast-1.amazonaws.com/dataset/487/487_frontal.jpg"
    ],
    "type": "apartment",
    "numberOfBeds": 4,
    "squareFeet": 262,
    "status": "rented",
    "location": {
      "city": "Hanoi",
      "district": "Ba Dinh"
    }
  },
  {
    "houseId": 2,
    "name": "Adipisicing sit consequat cillum sint.",
    "price": 218673,
    "description": "Reprehenderit minim aliqua exercitation esse est. Occaecat irure minim esse dolor est tempor enim velit velit.",
    "address": "Ut eu labore veniam aliquip.",
    "longitude": -52.391878,
    "latitude": 42.311699,
    "image": [
      "https://realestatemgt.s3.ap-southeast-1.amazonaws.com/dataset/398/398_bathroom.jpg",
      "https://realestatemgt.s3.ap-southeast-1.amazonaws.com/dataset/398/398_kitchen.jpg",
      "https://realestatemgt.s3.ap-southeast-1.amazonaws.com/dataset/398/398_bedroom.jpg",
      "https://realestatemgt.s3.ap-southeast-1.amazonaws.com/dataset/398/398_frontal.jpg"
    ],
    "type": "serviced",
    "numberOfBeds": 3,
    "squareFeet": 255,
    "status": "reserved",
    "location": {
      "city": "Hanoi",
      "district": "Ba Dinh"
    }
  },
  {
    "houseId": 3,
    "name": "Do ad tempor eiusmod mollit mollit eiusmod amet incididunt nostrud tempor.",
    "price": 147059,
    "description": "Incididunt irure culpa et ipsum nostrud exercitation aliqua.",
    "address": "Excepteur laboris commodo Lorem minim culpa mollit dolor excepteur aute tempor.",
    "longitude": -23.009296,
    "latitude": -38.207889,
    "image": [
      "https://realestatemgt.s3.ap-southeast-1.amazonaws.com/dataset/66/66_bathroom.jpg",
      "https://realestatemgt.s3.ap-southeast-1.amazonaws.com/dataset/66/66_kitchen.jpg",
      "https://realestatemgt.s3.ap-southeast-1.amazonaws.com/dataset/66/66_bedroom.jpg",
      "https://realestatemgt.s3.ap-southeast-1.amazonaws.com/dataset/66/66_frontal.jpg"
    ],
    "type": "street",
    "numberOfBeds": 3,
    "squareFeet": 294,
    "status": "reserved",
    "location": {
      "city": "Hanoi",
      "district": "Dong Da"
    }
  },
  {
    "houseId": 4,
    "name": "Ex ex tempor cillum fugiat nulla quis mollit sit commodo eu eu.",
    "price": 281705,
    "description": "Eiusmod proident aliquip reprehenderit ullamco.",
    "address": "Irure eiusmod velit consequat eu non reprehenderit.",
    "longitude": 160.756295,
    "latitude": 52.870153,
    "image": [
      "https://realestatemgt.s3.ap-southeast-1.amazonaws.com/dataset/202/202_bathroom.jpg",
      "https://realestatemgt.s3.ap-southeast-1.amazonaws.com/dataset/202/202_kitchen.jpg",
      "https://realestatemgt.s3.ap-southeast-1.amazonaws.com/dataset/202/202_bedroom.jpg",
      "https://realestatemgt.s3.ap-southeast-1.amazonaws.com/dataset/202/202_frontal.jpg"
    ],
    "type": "apartment",
    "numberOfBeds": 2,
    "squareFeet": 147,
    "status": "available",
    "location": {
      "city": "Saigon",
      "district": 4
    }
  },
  {
    "houseId": 5,
    "name": "Exercitation non qui incididunt aliqua occaecat adipisicing minim amet et veniam incididunt.",
    "price": 274849,
    "description": "Adipisicing culpa ullamco occaecat ex aliqua duis enim irure aliqua.",
    "address": "Et aute magna ad incididunt esse enim nostrud officia anim ad ad.",
    "longitude": -61.558664,
    "latitude": 24.10451,
    "image": [
      "https://realestatemgt.s3.ap-southeast-1.amazonaws.com/dataset/456/456_bathroom.jpg",
      "https://realestatemgt.s3.ap-southeast-1.amazonaws.com/dataset/456/456_kitchen.jpg",
      "https://realestatemgt.s3.ap-southeast-1.amazonaws.com/dataset/456/456_bedroom.jpg",
      "https://realestatemgt.s3.ap-southeast-1.amazonaws.com/dataset/456/456_frontal.jpg"
    ],
    "type": "apartment",
    "numberOfBeds": 3,
    "squareFeet": 183,
    "status": "reserved",
    "location": {
      "city": "Hanoi",
      "district": "Ba Dinh"
    }
  }
]
